{
    "BK-1771664274-1FF21CCC": {
        "email": "ninacross2002@yahoo.co.uk",
        "slot": "15:30",
        "title": "Ages 11-15 Skills Block (Southampton)",
        "date": "2026-03-01",
        "name": "Skylar Alldridge",
        "isBlock": true,
        "blockId": "block_1771599851110_9suv8hxol",
        "blockDates": [
            "2026-03-01",
            "2026-03-08",
            "2026-03-15",
            "2026-03-22"
        ],
        "price": null,
        "location": null,
        "status": "Confirmed",
        "confirmedAt": "2026-02-21T10:53:31.574Z",
        "createdAt": "2026-02-21 09:57:54"
    },
    "BK-1771685608-1CFB46A1": {
        "name": "Ethan Ashworth",
        "email": "roxy.ashworth@live.co.uk",
        "date": null,
        "slot": "15:30",
        "title": "Ages 11-15 Skills Block (Southampton)",
        "isBlock": true,
        "blockId": "block_1771599851110_9suv8hxol",
        "blockDates": [
            "2026-03-01",
            "2026-03-08",
            "2026-03-15",
            "2026-03-22"
        ],
        "price": null,
        "location": null,
        "status": "Confirmed",
        "confirmedAt": "2026-02-21T15:02:04.039Z",
        "createdAt": "2026-02-21 15:53:28",
        "timestamp": 1771685608,
        "reservationTimestamp": 1771685608,
        "expiryTimestamp": 1771772008
    },
    "BK-1771685696-A200DE1B": {
        "email": "roxy.ashworth@live.co.uk",
        "slot": "15:30",
        "title": "Ages 11-15 Skills Block (Southampton)",
        "date": "2026-03-01",
        "name": "Jacob Ashworth",
        "isBlock": true,
        "blockId": "block_1771599851110_9suv8hxol",
        "blockDates": [
            "2026-03-01",
            "2026-03-08",
            "2026-03-15",
            "2026-03-22"
        ],
        "price": null,
        "location": null,
        "status": "Confirmed",
        "confirmedAt": "2026-02-21T15:02:03.689Z",
        "createdAt": "2026-02-21 15:54:56"
    },
    "BK-1771693960-39DC2917": {
        "email": "ehornigold@gmail.com",
        "slot": "15:30",
        "title": "Ages 11-15 Skills Block (Southampton)",
        "date": "2026-03-01",
        "name": "Oscar Hornigold",
        "isBlock": true,
        "blockDates": [
            "2026-03-01",
            "2026-03-08",
            "2026-03-15",
            "2026-03-22"
        ],
        "status": "Confirmed",
        "confirmedAt": "2026-02-21T17:52:17.084Z",
        "createdAt": "2026-02-21 18:12:40"
    },
    "BK-1771694096-DB469E83": {
        "name": "Kane Cyrus",
        "email": "horace.cyrus@gmail.com",
        "date": null,
        "slot": "16:30",
        "title": "Ages 11-15 Skills Block (Portsmouth)",
        "isBlock": true,
        "blockId": "block_1771428514112_cjbr8jbo0",
        "blockDates": [
            "2026-02-25",
            "2026-03-04",
            "2026-03-11",
            "2026-03-18"
        ],
        "price": null,
        "location": null,
        "status": "Pending",
        "confirmedAt": null,
        "createdAt": "2026-02-21 18:14:56",
        "timestamp": 1771694096,
        "reservationTimestamp": 1771694096,
        "expiryTimestamp": 1771780496
    },
    "BK-1771700518-1213F51F": {
        "name": "2nd kid",
        "email": "aghacurtis@gmail.com",
        "date": null,
        "slot": "16:15",
        "title": "Ages 16-21 Skills Block (Southampton)",
        "isBlock": true,
        "blockId": "block_1771663570579_rtfxir9ps",
        "blockDates": [
            "2026-03-01",
            "2026-03-08",
            "2026-03-15",
            "2026-03-22"
        ],
        "price": null,
        "location": null,
        "status": "Pending",
        "confirmedAt": null,
        "createdAt": "2026-02-21 20:01:58",
        "timestamp": 1771700518,
        "reservationTimestamp": 1771700518,
        "expiryTimestamp": 1771786918
    }
}